meshagent/mcp/__init__.py
meshagent/mcp/cleanup.py
meshagent/mcp/toolkit.py
meshagent/mcp/version.py
meshagent_mcp-0.25.1.dist-info/licenses/LICENSE
meshagent_mcp-0.25.1.dist-info/METADATA
meshagent_mcp-0.25.1.dist-info/WHEEL
meshagent_mcp-0.25.1.dist-info/top_level.txt
meshagent_mcp-0.25.1.dist-info/RECORD
