Metadata-Version: 2.4
Name: meshagent-mcp
Version: 0.25.1
Summary: Computer Building Blocks for MCP
License-Expression: Apache-2.0
Project-URL: Documentation, https://docs.meshagent.com
Project-URL: Website, https://www.meshagent.com
Project-URL: Source, https://www.meshagent.com
Requires-Python: >=3.13
License-File: LICENSE
Requires-Dist: pytest~=8.4
Requires-Dist: pytest-asyncio~=0.26
Requires-Dist: mcp~=1.26.0
Requires-Dist: meshagent-tools~=0.25.1
Dynamic: license-file
